aiosfstream_ng/__init__.py
aiosfstream_ng/_metadata.py
aiosfstream_ng/auth.py
aiosfstream_ng/client.py
aiosfstream_ng/exceptions.py
aiosfstream_ng/py.typed
aiosfstream_ng/replay.py
aiosfstream_ng-0.7.5.dist-info/LICENSE.txt
aiosfstream_ng-0.7.5.dist-info/METADATA
aiosfstream_ng-0.7.5.dist-info/WHEEL
aiosfstream_ng-0.7.5.dist-info/top_level.txt
aiosfstream_ng-0.7.5.dist-info/RECORD
